setup.cfg
setup.py
adaptivepy/__init__.py
adaptivepy.egg-info/PKG-INFO
adaptivepy.egg-info/SOURCES.txt
adaptivepy.egg-info/dependency_links.txt
adaptivepy.egg-info/top_level.txt
adaptivepy/choice_strategies/__init__.py
adaptivepy/choice_strategies/restriction_based.py
adaptivepy/component/__init__.py
adaptivepy/component/adaptation_space.py
adaptivepy/component/adaptive.py
adaptivepy/component/adaptive_proxyrouter.py
adaptivepy/component/definitions.py
adaptivepy/component/proxy.py
adaptivepy/component/proxyrouter.py
adaptivepy/monitor/__init__.py
adaptivepy/monitor/base_implementations.py
adaptivepy/monitor/monitor_event_manager.py
adaptivepy/monitor/parameter.py
adaptivepy/monitor/parameter_event.py
adaptivepy/monitor/polling_dynamic_monitor.py
adaptivepy/monitor/primitives.py
adaptivepy/monitor/pull_dynamic_monitor.py
adaptivepy/tests/__init__.py
adaptivepy/tests/choice_strategies_tests/__init__.py
adaptivepy/tests/choice_strategies_tests/restriction_based_test.py
adaptivepy/tests/component_tests/__init__.py
adaptivepy/tests/component_tests/adaptation_space_test.py
adaptivepy/tests/component_tests/proxy_test.py
adaptivepy/tests/component_tests/proxyrouter_test.py
adaptivepy/tests/monitor_tests/__init__.py
adaptivepy/tests/monitor_tests/base_implementations_test.py
adaptivepy/tests/monitor_tests/monitor_event_manager_test.py
adaptivepy/tests/monitor_tests/parameter_test.py
adaptivepy/tests/monitor_tests/pull_dynamic_monitor_test.py
adaptivepy/tests/util_tests/__init__.py
adaptivepy/tests/util_tests/double_indexed_dictionary_test.py
adaptivepy/util/__init__.py
adaptivepy/util/double_indexed_dictionary.py
adaptivepy/util/observer_pattern.py